Workbook

Sheet Leia-me
A1: Modelo de custos e ROI do canal Wise Partners
A2: Referência de cálculo do portal (spec 002, Apêndice M). O portal deve chegar aos mesmos números para as mesmas entradas (SC-101).
A4: Como usar
A5: 1. Células em azul com fundo amarelo são entradas: edite só elas. Células em preto são fórmulas.
A6: 2. Parametros: remuneração, horas de referência, fator de encargos, horizonte de receita, prazo padrão, margem e o período do cálculo.
A7: 3. Pessoas: uma linha por pessoa que registra atividades. Sem remuneração, o custo-hora fica zero e o ROI fica subestimado.
A8: 4. Atividades: catálogo de esforço (Apêndice N), com minutos estimados e custo estimado pelo custo-hora do Guilherme.
A9: 5. Horas, Custos_Diretos, Receita_Comissoes e Comissoes_Recebidas: lançamentos. As linhas cinza marcadas EXEMPLO reproduzem o cenário da História 1 do spec; apague-as antes de usar.
A10: 6. ROI: resultado do período e por parceiro.
A12: Premissas
A13: Remuneração de referência do Guilherme Faccin: R$ 4.500,00 por mês, informada por ele para este cálculo. 220 horas mensais (44 horas semanais). Fator de encargos 1,0 a pedido; mude para incluir encargos e benefícios.
A14: Receita atribuída: Wise Makers = mensalidade x mínimo entre prazo do contrato e horizonte; Tríade e Swallow = valor total da venda. Somam-se as comissões recebidas de parceiros.
... A17: Fase do programa: experimentação. Pelo livro, investimento maior que retorno é esperado nesta fase.

Sheet Parametros
A1: Parâmetro | B1: Valor | C1: Observação
A2: Horas mensais de referência | B2: 220 | C2: 44 horas semanais
A3: Fator de encargos | B3: 1 | C3: 1,0 = só a remuneração informada
A4: Horizonte de receita (meses) | B4: 12 | C4: Receita da Wise conta até este número de meses
A5: Prazo padrão do contrato (meses) | B5: 12 | C5: Usado quando a indicação não informa o prazo
A6: Margem de contribuição | B6: 1 | C6: 100% = ROI sobre a receita
A7: Início do período | B7: 46296 | C7: Período do cálculo do ROI
A8: Fim do período | B8: 46752
A11: Regras de comissão por empresa
A12: Empresa | B12: % parceiro | C12: % responsável
A13: Wise Makers | B13: 0.4 | C13: 0.1
A14: Tríade | B14: 0.4 | C14: 0.1
A15: Swallow | B15: 0.06 | C15: 0.02
A17: Fonte: Apêndice A do spec 001 (regras de comissão vigentes).

Sheet Pessoas
A1: Pessoa | B1: Remuneração mensal (R$) | C1: Horas mensais | D1: Fator de encargos | E1: Custo-hora (R$) | F1: Custo por minuto (R$)
A2: Guilherme Faccin | B2: 4500 | C2: =Parametros!$B$2 -> 220 | D2: =Parametros!$B$3 -> 1 | E2: =IF(B2="",0,B2/C2*D2) -> 20.454545 | F2: =E2/60 -> 0.34090909
A3: Igor Makoto | C3: =Parametros!$B$2 -> 220 | D3: =Parametros!$B$3 -> 1 | E3: =IF(B3="",0,B3/C3*D3) -> 0 | F3: =E3/60 -> 0
A4: Remuneração do Igor a informar. Sem ela, as horas dele entram com custo zero.

Sheet Atividades
A1: Etapa | B1: Atividade | C1: Minutos estimados | D1: Custo estimado pelo custo-hora do Guilherme (R$)
A2: Captação | B2: Pesquisa e preparação da abordagem | C2: 20 | D2: =C2*Pessoas!$F$2 -> 6.8181818
A3: Captação | B3: Mensagem ou follow-up | C3: 5 | D3: =C3*Pessoas!$F$2 -> 1.7045455
A4: Captação | B4: Ligação | C4: 15 | D4: =C4*Pessoas!$F$2 -> 5.1136364
A5: Captação | B5: Reunião de apresentação (45 min mais preparação) | C5: 75 | D5: =C5*Pessoas!$F$2 -> 25.568182
A6: Captação | B6: Preparação de dossiê ou apresentação personalizada | C6: 60 | D6: =C6*Pessoas!$F$2 -> 20.454545
A7: Captação | B7: Preenchimento do scorecard | C7: 15 | D7: =C7*Pessoas!$F$2 -> 5.1136364
A8: Captação | B8: Negociação e ajuste de proposta | C8: 45 | D8: =C8*Pessoas!$F$2 -> 15.340909
A9: Captação | B9: Documento enviado (minuta, resumo, proposta) | C9: 30 | D9: =C9*Pessoas!$F$2 -> 10.227273
A10: Captação | B10: Geração e revisão da minuta de contrato | C10: 30 | D10: =C10*Pessoas!$F$2 -> 10.227273
A11: Captação | B11: Aprovação de assinatura com o Diretor | C11: 15 | D11: =C11*Pessoas!$F$2 -> 5.1136364
A12: Captação | B12: Contato de nutrição | C12: 10 | D12: =C12*Pessoas!$F$2 -> 3.4090909
A13: Onboarding | B13: Tarefas de implantação do pacote | C13: 60 | D13: =C13*Pessoas!$F$2 -> 20.454545
... A40: Gestão | B40: Gestão geral do programa (sem parceiro) | C40: 60 | D40: =C40*Pessoas!$F$2 -> 20.454545

Sheet Horas
A1: Data | B1: Pessoa | C1: Parceiro | D1: Atividade | E1: Minutos | F1: Custo-hora (R$) | G1: Custo (R$) | H1: Marcação
A2: 46329 | B2: Guilherme Faccin | C2: Parceiro Exemplo | D2: Reunião de apresentação (45 min mais preparação) | E2: 600 | F2: =IFERROR(INDEX(Pessoas!$E:$E,MATCH(B2,Pessoas!$A:$A,0)),0) -> 20.454545 | G2: =E2/60*F2 -> 204.54545 | H2: EXEMPLO
A3: 46336 | B3: Guilherme Faccin | C3: Parceiro Exemplo | D3: Encontro de alinhamento | E3: 480 | F3: =IFERROR(INDEX(Pessoas!$E:$E,MATCH(B3,Pessoas!$A:$A,0)),0) -> 20.454545 | G3: =E3/60*F3 -> 163.63636 | H3: EXEMPLO
A4: 46343 | B4: Guilherme Faccin | C4: Parceiro Exemplo | D4: Check-in mensal | E4: 360 | F4: =IFERROR(INDEX(Pessoas!$E:$E,MATCH(B4,Pessoas!$A:$A,0)),0) -> 20.454545 | G4: =E4/60*F4 -> 122.72727 | H4: EXEMPLO
A5: 46350 | B5: Guilherme Faccin | C5: Parceiro Exemplo | D5: Tratamento de indicação (validação e repasse) | E5: 240 | F5: =IFERROR(INDEX(Pessoas!$E:$E,MATCH(B5,Pessoas!$A:$A,0)),0) -> 20.454545 | G5: =E5/60*F5 -> 81.818182 | H5: EXEMPLO
A6: 46352 | B6: Guilherme Faccin | C6: Geral do programa | D6: Gestão geral do programa (sem parceiro) | E6: 240 | F6: =IFERROR(INDEX(Pessoas!$E:$E,MATCH(B6,Pessoas!$A:$A,0)),0) -> 20.454545 | G6: =E6/60*F6 -> 81.818182 | H6: EXEMPLO
A7: 46353 | B7: Guilherme Faccin | C7: Parceiro Exemplo | D7: Revisão semanal com o Diretor | E7: 480 | F7: =IFERROR(INDEX(Pessoas!$E:$E,MATCH(B7,Pessoas!$A:$A,0)),0) -> 20.454545 | G7: =E7/60*F7 -> 163.63636 | H7: EXEMPLO
F8: =IF(B8="","",IFERROR(INDEX(Pessoas!$E:$E,MATCH(B8,Pessoas!$A:$A,0)),0)) | G8: =IF(E8="","",E8/60*F8)
F9: =IF(B9="","",IFERROR(INDEX(Pessoas!$E:$E,MATCH(B9,Pessoas!$A:$A,0)),0)) | G9: =IF(E9="","",E9/60*F9)
F10: =IF(B10="","",IFERROR(INDEX(Pessoas!$E:$E,MATCH(B10,Pessoas!$A:$A,0)),0)) | G10: =IF(E10="","",E10/60*F10)
F11: =IF(B11="","",IFERROR(INDEX(Pessoas!$E:$E,MATCH(B11,Pessoas!$A:$A,0)),0)) | G11: =IF(E11="","",E11/60*F11)
F12: =IF(B12="","",IFERROR(INDEX(Pessoas!$E:$E,MATCH(B12,Pessoas!$A:$A,0)),0)) | G12: =IF(E12="","",E12/60*F12)
F13: =IF(B13="","",IFERROR(INDEX(Pessoas!$E:$E,MATCH(B13,Pessoas!$A:$A,0)),0)) | G13: =IF(E13="","",E13/60*F13)
F14: =IF(B14="","",IFERROR(INDEX(Pessoas!$E:$E,MATCH(B14,Pessoas!$A:$A,0)),0)) | G14: =IF(E14="","",E14/60*F14)
F15: =IF(B15="","",IFERROR(INDEX(Pessoas!$E:$E,MATCH(B15,Pessoas!$A:$A,0)),0)) | G15: =IF(E15="","",E15/60*F15)
F16: =IF(B16="","",IFERROR(INDEX(Pessoas!$E:$E,MATCH(B16,Pessoas!$A:$A,0)),0)) | G16: =IF(E16="","",E16/60*F16)
F17: =IF(B17="","",IFERROR(INDEX(Pessoas!$E:$E,MATCH(B17,Pessoas!$A:$A,0)),0)) | G17: =IF(E17="","",E17/60*F17)
F18: =IF(B18="","",IFERROR(INDEX(Pessoas!$E:$E,MATCH(B18,Pessoas!$A:$A,0)),0)) | G18: =IF(E18="","",E18/60*F18)
F19: =IF(B19="","",IFERROR(INDEX(Pessoas!$E:$E,MATCH(B19,Pessoas!$A:$A,0)),0)) | G19: =IF(E19="","",E19/60*F19)
... F500: =IF(B500="","",IFERROR(INDEX(Pessoas!$E:$E,MATCH(B500,Pessoas!$A:$A,0)),0)) | G500: =IF(E500="","",E500/60*F500)

Sheet Custos_Diretos
A1: Data | B1: Categoria | C1: Parceiro | D1: Descrição | E1: Valor (R$) | F1: Marcação
A2: 46346 | B2: Evento | C2: Parceiro Exemplo | D2: Café da manhã com a carteira do parceiro | E2: 500 | F2: EXEMPLO

Sheet Receita_Comissoes
A1: Data de fechamento | B1: Parceiro | C1: Empresa do grupo | D1: Cliente | E1: No ICP (Sim/Não) | F1: Mensalidade (R$, Wise) | G1: Prazo do contrato (meses) | H1: Valor total da venda (R$, Tríade ou Swallow) | I1: Base da comissão (R$) | J1: Receita atribuída (R$) | K1: Comissão ao parceiro (R$) | L1: Comissão ao responsável (R$) | M1: Mensalidade recorrente (R$) | N1: Marcação
A2: 46366 | B2: Parceiro Exemplo | C2: Wise Makers | D2: Indústria Exemplo Ltda | E2: Sim | F2: 6000 | G2: 12 | I2: 6000 | J2: =IF(A2="","",IF(C2="Wise Makers",F2*MIN(IF(G2="",Parametros!$B$5,G2),Parametros!$B$4),H2)) -> 72000 | K2: =IF(A2="","",I2*IFERROR(INDEX(Parametros!$B$13:$B$15,MATCH(C2,Parametros!$A$13:$A$15,0)),0)) -> 2400 | L2: =IF(A2="","",I2*IFERROR(INDEX(Parametros!$C$13:$C$15,MATCH(C2,Parametros!$A$13:$A$15,0)),0)) -> 600 | M2: =IF(A2="","",IF(C2="Wise Makers",F2,0)) -> 6000 | N2: EXEMPLO
J3: =IF(A3="","",IF(C3="Wise Makers",F3*MIN(IF(G3="",Parametros!$B$5,G3),Parametros!$B$4),H3)) | K3: =IF(A3="","",I3*IFERROR(INDEX(Parametros!$B$13:$B$15,MATCH(C3,Parametros!$A$13:$A$15,0)),0)) | L3: =IF(A3="","",I3*IFERROR(INDEX(Parametros!$C$13:$C$15,MATCH(C3,Parametros!$A$13:$A$15,0)),0)) | M3: =IF(A3="","",IF(C3="Wise Makers",F3,0))
J4: =IF(A4="","",IF(C4="Wise Makers",F4*MIN(IF(G4="",Parametros!$B$5,G4),Parametros!$B$4),H4)) | K4: =IF(A4="","",I4*IFERROR(INDEX(Parametros!$B$13:$B$15,MATCH(C4,Parametros!$A$13:$A$15,0)),0)) | L4: =IF(A4="","",I4*IFERROR(INDEX(Parametros!$C$13:$C$15,MATCH(C4,Parametros!$A$13:$A$15,0)),0)) | M4: =IF(A4="","",IF(C4="Wise Makers",F4,0))
J5: =IF(A5="","",IF(C5="Wise Makers",F5*MIN(IF(G5="",Parametros!$B$5,G5),Parametros!$B$4),H5)) | K5: =IF(A5="","",I5*IFERROR(INDEX(Parametros!$B$13:$B$15,MATCH(C5,Parametros!$A$13:$A$15,0)),0)) | L5: =IF(A5="","",I5*IFERROR(INDEX(Parametros!$C$13:$C$15,MATCH(C5,Parametros!$A$13:$A$15,0)),0)) | M5: =IF(A5="","",IF(C5="Wise Makers",F5,0))
J6: =IF(A6="","",IF(C6="Wise Makers",F6*MIN(IF(G6="",Parametros!$B$5,G6),Parametros!$B$4),H6)) | K6: =IF(A6="","",I6*IFERROR(INDEX(Parametros!$B$13:$B$15,MATCH(C6,Parametros!$A$13:$A$15,0)),0)) | L6: =IF(A6="","",I6*IFERROR(INDEX(Parametros!$C$13:$C$15,MATCH(C6,Parametros!$A$13:$A$15,0)),0)) | M6: =IF(A6="","",IF(C6="Wise Makers",F6,0))
J7: =IF(A7="","",IF(C7="Wise Makers",F7*MIN(IF(G7="",Parametros!$B$5,G7),Parametros!$B$4),H7)) | K7: =IF(A7="","",I7*IFERROR(INDEX(Parametros!$B$13:$B$15,MATCH(C7,Parametros!$A$13:$A$15,0)),0)) | L7: =IF(A7="","",I7*IFERROR(INDEX(Parametros!$C$13:$C$15,MATCH(C7,Parametros!$A$13:$A$15,0)),0)) | M7: =IF(A7="","",IF(C7="Wise Makers",F7,0))
J8: =IF(A8="","",IF(C8="Wise Makers",F8*MIN(IF(G8="",Parametros!$B$5,G8),Parametros!$B$4),H8)) | K8: =IF(A8="","",I8*IFERROR(INDEX(Parametros!$B$13:$B$15,MATCH(C8,Parametros!$A$13:$A$15,0)),0)) | L8: =IF(A8="","",I8*IFERROR(INDEX(Parametros!$C$13:$C$15,MATCH(C8,Parametros!$A$13:$A$15,0)),0)) | M8: =IF(A8="","",IF(C8="Wise Makers",F8,0))
J9: =IF(A9="","",IF(C9="Wise Makers",F9*MIN(IF(G9="",Parametros!$B$5,G9),Parametros!$B$4),H9)) | K9: =IF(A9="","",I9*IFERROR(INDEX(Parametros!$B$13:$B$15,MATCH(C9,Parametros!$A$13:$A$15,0)),0)) | L9: =IF(A9="","",I9*IFERROR(INDEX(Parametros!$C$13:$C$15,MATCH(C9,Parametros!$A$13:$A$15,0)),0)) | M9: =IF(A9="","",IF(C9="Wise Makers",F9,0))
J10: =IF(A10="","",IF(C10="Wise Makers",F10*MIN(IF(G10="",Parametros!$B$5,G10),Parametros!$B$4),H10)) | K10: =IF(A10="","",I10*IFERROR(INDEX(Parametros!$B$13:$B$15,MATCH(C10,Parametros!$A$13:$A$15,0)),0)) | L10: =IF(A10="","",I10*IFERROR(INDEX(Parametros!$C$13:$C$15,MATCH(C10,Parametros!$A$13:$A$15,0)),0)) | M10: =IF(A10="","",IF(C10="Wise Makers",F10,0))
J11: =IF(A11="","",IF(C11="Wise Makers",F11*MIN(IF(G11="",Parametros!$B$5,G11),Parametros!$B$4),H11)) | K11: =IF(A11="","",I11*IFERROR(INDEX(Parametros!$B$13:$B$15,MATCH(C11,Parametros!$A$13:$A$15,0)),0)) | L11: =IF(A11="","",I11*IFERROR(INDEX(Parametros!$C$13:$C$15,MATCH(C11,Parametros!$A$13:$A$15,0)),0)) | M11: =IF(A11="","",IF(C11="Wise Makers",F11,0))
J12: =IF(A12="","",IF(C12="Wise Makers",F12*MIN(IF(G12="",Parametros!$B$5,G12),Parametros!$B$4),H12)) | K12: =IF(A12="","",I12*IFERROR(INDEX(Parametros!$B$13:$B$15,MATCH(C12,Parametros!$A$13:$A$15,0)),0)) | L12: =IF(A12="","",I12*IFERROR(INDEX(Parametros!$C$13:$C$15,MATCH(C12,Parametros!$A$13:$A$15,0)),0)) | M12: =IF(A12="","",IF(C12="Wise Makers",F12,0))
J13: =IF(A13="","",IF(C13="Wise Makers",F13*MIN(IF(G13="",Parametros!$B$5,G13),Parametros!$B$4),H13)) | K13: =IF(A13="","",I13*IFERROR(INDEX(Parametros!$B$13:$B$15,MATCH(C13,Parametros!$A$13:$A$15,0)),0)) | L13: =IF(A13="","",I13*IFERROR(INDEX(Parametros!$C$13:$C$15,MATCH(C13,Parametros!$A$13:$A$15,0)),0)) | M13: =IF(A13="","",IF(C13="Wise Makers",F13,0))
J14: =IF(A14="","",IF(C14="Wise Makers",F14*MIN(IF(G14="",Parametros!$B$5,G14),Parametros!$B$4),H14)) | K14: =IF(A14="","",I14*IFERROR(INDEX(Parametros!$B$13:$B$15,MATCH(C14,Parametros!$A$13:$A$15,0)),0)) | L14: =IF(A14="","",I14*IFERROR(INDEX(Parametros!$C$13:$C$15,MATCH(C14,Parametros!$A$13:$A$15,0)),0)) | M14: =IF(A14="","",IF(C14="Wise Makers",F14,0))
... J300: =IF(A300="","",IF(C300="Wise Makers",F300*MIN(IF(G300="",Parametros!$B$5,G300),Parametros!$B$4),H300)) | K300: =IF(A300="","",I300*IFERROR(INDEX(Parametros!$B$13:$B$15,MATCH(C300,Parametros!$A$13:$A$15,0)),0)) | L300: =IF(A300="","",I300*IFERROR(INDEX(Parametros!$C$13:$C$15,MATCH(C300,Parametros!$A$13:$A$15,0)),0)) | M300: =IF(A300="","",IF(C300="Wise Makers",F300,0))

Sheet Comissoes_Recebidas
A1: Data do pagamento | B1: Parceiro | C1: Cliente indicado pelo grupo | D1: Valor recebido (R$) | E1: Marcação

Sheet ROI
A1: ROI do canal no período
A2: Período | B2: =Parametros!B7 -> 46296 | C2: =Parametros!B8 -> 46752
A3: Indicador | B3: Valor | C3: Como é calculado
A4: Valores do período definido em Parametros
A5: Horas registradas | B5: =SUMIFS(Horas!$E:$E,Horas!$A:$A,">="&Parametros!$B$7,Horas!$A:$A,"<="&Parametros!$B$8)/60 -> 40 | C5: Total de horas de todas as pessoas
A6: Custo das horas | B6: =SUMIFS(Horas!$G:$G,Horas!$A:$A,">="&Parametros!$B$7,Horas!$A:$A,"<="&Parametros!$B$8) -> 818.18182 | C6: Horas x custo-hora
A7: Comissões ao parceiro | B7: =SUMIFS(Receita_Comissoes!$K:$K,Receita_Comissoes!$A:$A,">="&Parametros!$B$7,Receita_Comissoes!$A:$A,"<="&Parametros!$B$8) -> 2400
A8: Comissões ao responsável | B8: =SUMIFS(Receita_Comissoes!$L:$L,Receita_Comissoes!$A:$A,">="&Parametros!$B$7,Receita_Comissoes!$A:$A,"<="&Parametros!$B$8) -> 600
A9: Custos diretos | B9: =SUMIFS(Custos_Diretos!$E:$E,Custos_Diretos!$A:$A,">="&Parametros!$B$7,Custos_Diretos!$A:$A,"<="&Parametros!$B$8) -> 500
A10: Custo total do canal | B10: =SUM(B6:B9) -> 4318.1818
A11: Receita atribuída de clientes | B11: =SUMIFS(Receita_Comissoes!$J:$J,Receita_Comissoes!$A:$A,">="&Parametros!$B$7,Receita_Comissoes!$A:$A,"<="&Parametros!$B$8) -> 72000
A12: Comissões recebidas de parceiros | B12: =SUMIFS(Comissoes_Recebidas!$D:$D,Comissoes_Recebidas!$A:$A,">="&Parametros!$B$7,Comissoes_Recebidas!$A:$A,"<="&Parametros!$B$8) -> 0
A13: Receita atribuída total | B13: =B11+B12 -> 72000
A14: Receita x margem de contribuição | B14: =B13*Parametros!$B$6 -> 72000
A15: ROI | B15: =IF(B10=0,"",(B14-B10)/B10) -> 15.673684 | C15: (receita x margem menos custo) dividido pelo custo
A16: Clientes fechados no ICP | B16: =COUNTIFS(Receita_Comissoes!$A:$A,">="&Parametros!$B$7,Receita_Comissoes!$A:$A,"<="&Parametros!$B$8,Receita_Comissoes!$E:$E,"Sim") -> 1 | C16: Número principal do programa
A17: Custo por cliente no ICP | B17: =IF(B16=0,"",B10/B16) -> 4318.1818
A18: Mensalidade recorrente dos clientes do canal | B18: =SUMIFS(Receita_Comissoes!$M:$M,Receita_Comissoes!$A:$A,">="&Parametros!$B$7,Receita_Comissoes!$A:$A,"<="&Parametros!$B$8) -> 6000
A19: Tempo de retorno (meses) | B19: =IF(B18*Parametros!$B$6=0,"",B10/(B18*Parametros!$B$6)) -> 0.71969697 | C19: Custo dividido pela mensalidade recorrente x margem
A20: ROI por parceiro no período (custo geral do programa fica à parte, sem rateio)
A21: Parceiro | B21: Horas | C21: Custo das horas (R$) | D21: Comissões pagas (R$) | E21: Custos diretos (R$) | F21: Custo total (R$) | G21: Receita atribuída (R$) | H21: Clientes no ICP | I21: ROI
A22: Parceiro Exemplo | B22: =SUMIFS(Horas!$E:$E,Horas!$C:$C,$A22,Horas!$A:$A,">="&Parametros!$B$7,Horas!$A:$A,"<="&Parametros!$B$8)/60 -> 36 | C22: =SUMIFS(Horas!$G:$G,Horas!$C:$C,$A22,Horas!$A:$A,">="&Parametros!$B$7,Horas!$A:$A,"<="&Parametros!$B$8) -> 736.36364 | D22: =SUMIFS(Receita_Comissoes!$K:$K,Receita_Comissoes!$B:$B,$A22,Receita_Comissoes!$A:$A,">="&Parametros!$B$7,Receita_Comissoes!$A:$A,"<="&Parametros!$B$8)+SUMIFS(Receita_Comissoes!$L:$L,Receita_Comissoes!$B:$B,$A22,Receita_Comissoes!$A:$A,">="&Parametros!$B$7,Receita_Comissoes!$A:$A,"<="&Parametros!$B$8) -> 3000 | E22: =SUMIFS(Custos_Diretos!$E:$E,Custos_Diretos!$C:$C,$A22,Custos_Diretos!$A:$A,">="&Parametros!$B$7,Custos_Diretos!$A:$A,"<="&Parametros!$B$8) -> 500 | F22: =C22+D22+E22 -> 4236.3636 | G22: =SUMIFS(Receita_Comissoes!$J:$J,Receita_Comissoes!$B:$B,$A22,Receita_Comissoes!$A:$A,">="&Parametros!$B$7,Receita_Comissoes!$A:$A,"<="&Parametros!$B$8)+SUMIFS(Comissoes_Recebidas!$D:$D,Comissoes_Recebidas!$B:$B,$A22,Comissoes_Recebidas!$A:$A,">="&Parametros!$B$7,Comissoes_Recebidas!$A:$A,"<="&Parametros!$B$8) -> 72000 | H22: =COUNTIFS(Receita_Comissoes!$B:$B,$A22,Receita_Comissoes!$E:$E,"Sim",Receita_Comissoes!$A:$A,">="&Parametros!$B$7,Receita_Comissoes!$A:$A,"<="&Parametros!$B$8) -> 1 | I22: =IF(F22=0,"",(G22*Parametros!$B$6-F22)/F22) -> 15.995708
A23: Consistem | B23: =SUMIFS(Horas!$E:$E,Horas!$C:$C,$A23,Horas!$A:$A,">="&Parametros!$B$7,Horas!$A:$A,"<="&Parametros!$B$8)/60 -> 0 | C23: =SUMIFS(Horas!$G:$G,Horas!$C:$C,$A23,Horas!$A:$A,">="&Parametros!$B$7,Horas!$A:$A,"<="&Parametros!$B$8) -> 0 | D23: =SUMIFS(Receita_Comissoes!$K:$K,Receita_Comissoes!$B:$B,$A23,Receita_Comissoes!$A:$A,">="&Parametros!$B$7,Receita_Comissoes!$A:$A,"<="&Parametros!$B$8)+SUMIFS(Receita_Comissoes!$L:$L,Receita_Comissoes!$B:$B,$A23,Receita_Comissoes!$A:$A,">="&Parametros!$B$7,Receita_Comissoes!$A:$A,"<="&Parametros!$B$8) -> 0 | E23: =SUMIFS(Custos_Diretos!$E:$E,Custos_Diretos!$C:$C,$A23,Custos_Diretos!$A:$A,">="&Parametros!$B$7,Custos_Diretos!$A:$A,"<="&Parametros!$B$8) -> 0 | F23: =C23+D23+E23 -> 0 | G23: =SUMIFS(Receita_Comissoes!$J:$J,Receita_Comissoes!$B:$B,$A23,Receita_Comissoes!$A:$A,">="&Parametros!$B$7,Receita_Comissoes!$A:$A,"<="&Parametros!$B$8)+SUMIFS(Comissoes_Recebidas!$D:$D,Comissoes_Recebidas!$B:$B,$A23,Comissoes_Recebidas!$A:$A,">="&Parametros!$B$7,Comissoes_Recebidas!$A:$A,"<="&Parametros!$B$8) -> 0 | H23: =COUNTIFS(Receita_Comissoes!$B:$B,$A23,Receita_Comissoes!$E:$E,"Sim",Receita_Comissoes!$A:$A,">="&Parametros!$B$7,Receita_Comissoes!$A:$A,"<="&Parametros!$B$8) -> 0 | I23: =IF(F23=0,"",(G23*Parametros!$B$6-F23)/F23)
A24: Brasão Sistemas | B24: =SUMIFS(Horas!$E:$E,Horas!$C:$C,$A24,Horas!$A:$A,">="&Parametros!$B$7,Horas!$A:$A,"<="&Parametros!$B$8)/60 -> 0 | C24: =SUMIFS(Horas!$G:$G,Horas!$C:$C,$A24,Horas!$A:$A,">="&Parametros!$B$7,Horas!$A:$A,"<="&Parametros!$B$8) -> 0 | D24: =SUMIFS(Receita_Comissoes!$K:$K,Receita_Comissoes!$B:$B,$A24,Receita_Comissoes!$A:$A,">="&Parametros!$B$7,Receita_Comissoes!$A:$A,"<="&Parametros!$B$8)+SUMIFS(Receita_Comissoes!$L:$L,Receita_Comissoes!$B:$B,$A24,Receita_Comissoes!$A:$A,">="&Parametros!$B$7,Receita_Comissoes!$A:$A,"<="&Parametros!$B$8) -> 0 | E24: =SUMIFS(Custos_Diretos!$E:$E,Custos_Diretos!$C:$C,$A24,Custos_Diretos!$A:$A,">="&Parametros!$B$7,Custos_Diretos!$A:$A,"<="&Parametros!$B$8) -> 0 | F24: =C24+D24+E24 -> 0 | G24: =SUMIFS(Receita_Comissoes!$J:$J,Receita_Comissoes!$B:$B,$A24,Receita_Comissoes!$A:$A,">="&Parametros!$B$7,Receita_Comissoes!$A:$A,"<="&Parametros!$B$8)+SUMIFS(Comissoes_Recebidas!$D:$D,Comissoes_Recebidas!$B:$B,$A24,Comissoes_Recebidas!$A:$A,">="&Parametros!$B$7,Comissoes_Recebidas!$A:$A,"<="&Parametros!$B$8) -> 0 | H24: =COUNTIFS(Receita_Comissoes!$B:$B,$A24,Receita_Comissoes!$E:$E,"Sim",Receita_Comissoes!$A:$A,">="&Parametros!$B$7,Receita_Comissoes!$A:$A,"<="&Parametros!$B$8) -> 0 | I24: =IF(F24=0,"",(G24*Parametros!$B$6-F24)/F24)
A25: iPro CRM | B25: =SUMIFS(Horas!$E:$E,Horas!$C:$C,$A25,Horas!$A:$A,">="&Parametros!$B$7,Horas!$A:$A,"<="&Parametros!$B$8)/60 -> 0 | C25: =SUMIFS(Horas!$G:$G,Horas!$C:$C,$A25,Horas!$A:$A,">="&Parametros!$B$7,Horas!$A:$A,"<="&Parametros!$B$8) -> 0 | D25: =SUMIFS(Receita_Comissoes!$K:$K,Receita_Comissoes!$B:$B,$A25,Receita_Comissoes!$A:$A,">="&Parametros!$B$7,Receita_Comissoes!$A:$A,"<="&Parametros!$B$8)+SUMIFS(Receita_Comissoes!$L:$L,Receita_Comissoes!$B:$B,$A25,Receita_Comissoes!$A:$A,">="&Parametros!$B$7,Receita_Comissoes!$A:$A,"<="&Parametros!$B$8) -> 0 | E25: =SUMIFS(Custos_Diretos!$E:$E,Custos_Diretos!$C:$C,$A25,Custos_Diretos!$A:$A,">="&Parametros!$B$7,Custos_Diretos!$A:$A,"<="&Parametros!$B$8) -> 0 | F25: =C25+D25+E25 -> 0 | G25: =SUMIFS(Receita_Comissoes!$J:$J,Receita_Comissoes!$B:$B,$A25,Receita_Comissoes!$A:$A,">="&Parametros!$B$7,Receita_Comissoes!$A:$A,"<="&Parametros!$B$8)+SUMIFS(Comissoes_Recebidas!$D:$D,Comissoes_Recebidas!$B:$B,$A25,Comissoes_Recebidas!$A:$A,">="&Parametros!$B$7,Comissoes_Recebidas!$A:$A,"<="&Parametros!$B$8) -> 0 | H25: =COUNTIFS(Receita_Comissoes!$B:$B,$A25,Receita_Comissoes!$E:$E,"Sim",Receita_Comissoes!$A:$A,">="&Parametros!$B$7,Receita_Comissoes!$A:$A,"<="&Parametros!$B$8) -> 0 | I25: =IF(F25=0,"",(G25*Parametros!$B$6-F25)/F25)
A26: Intalenti | B26: =SUMIFS(Horas!$E:$E,Horas!$C:$C,$A26,Horas!$A:$A,">="&Parametros!$B$7,Horas!$A:$A,"<="&Parametros!$B$8)/60 -> 0 | C26: =SUMIFS(Horas!$G:$G,Horas!$C:$C,$A26,Horas!$A:$A,">="&Parametros!$B$7,Horas!$A:$A,"<="&Parametros!$B$8) -> 0 | D26: =SUMIFS(Receita_Comissoes!$K:$K,Receita_Comissoes!$B:$B,$A26,Receita_Comissoes!$A:$A,">="&Parametros!$B$7,Receita_Comissoes!$A:$A,"<="&Parametros!$B$8)+SUMIFS(Receita_Comissoes!$L:$L,Receita_Comissoes!$B:$B,$A26,Receita_Comissoes!$A:$A,">="&Parametros!$B$7,Receita_Comissoes!$A:$A,"<="&Parametros!$B$8) -> 0 | E26: =SUMIFS(Custos_Diretos!$E:$E,Custos_Diretos!$C:$C,$A26,Custos_Diretos!$A:$A,">="&Parametros!$B$7,Custos_Diretos!$A:$A,"<="&Parametros!$B$8) -> 0 | F26: =C26+D26+E26 -> 0 | G26: =SUMIFS(Receita_Comissoes!$J:$J,Receita_Comissoes!$B:$B,$A26,Receita_Comissoes!$A:$A,">="&Parametros!$B$7,Receita_Comissoes!$A:$A,"<="&Parametros!$B$8)+SUMIFS(Comissoes_Recebidas!$D:$D,Comissoes_Recebidas!$B:$B,$A26,Comissoes_Recebidas!$A:$A,">="&Parametros!$B$7,Comissoes_Recebidas!$A:$A,"<="&Parametros!$B$8) -> 0 | H26: =COUNTIFS(Receita_Comissoes!$B:$B,$A26,Receita_Comissoes!$E:$E,"Sim",Receita_Comissoes!$A:$A,">="&Parametros!$B$7,Receita_Comissoes!$A:$A,"<="&Parametros!$B$8) -> 0 | I26: =IF(F26=0,"",(G26*Parametros!$B$6-F26)/F26)
A27: GRV Software | B27: =SUMIFS(Horas!$E:$E,Horas!$C:$C,$A27,Horas!$A:$A,">="&Parametros!$B$7,Horas!$A:$A,"<="&Parametros!$B$8)/60 -> 0 | C27: =SUMIFS(Horas!$G:$G,Horas!$C:$C,$A27,Horas!$A:$A,">="&Parametros!$B$7,Horas!$A:$A,"<="&Parametros!$B$8) -> 0 | D27: =SUMIFS(Receita_Comissoes!$K:$K,Receita_Comissoes!$B:$B,$A27,Receita_Comissoes!$A:$A,">="&Parametros!$B$7,Receita_Comissoes!$A:$A,"<="&Parametros!$B$8)+SUMIFS(Receita_Comissoes!$L:$L,Receita_Comissoes!$B:$B,$A27,Receita_Comissoes!$A:$A,">="&Parametros!$B$7,Receita_Comissoes!$A:$A,"<="&Parametros!$B$8) -> 0 | E27: =SUMIFS(Custos_Diretos!$E:$E,Custos_Diretos!$C:$C,$A27,Custos_Diretos!$A:$A,">="&Parametros!$B$7,Custos_Diretos!$A:$A,"<="&Parametros!$B$8) -> 0 | F27: =C27+D27+E27 -> 0 | G27: =SUMIFS(Receita_Comissoes!$J:$J,Receita_Comissoes!$B:$B,$A27,Receita_Comissoes!$A:$A,">="&Parametros!$B$7,Receita_Comissoes!$A:$A,"<="&Parametros!$B$8)+SUMIFS(Comissoes_Recebidas!$D:$D,Comissoes_Recebidas!$B:$B,$A27,Comissoes_Recebidas!$A:$A,">="&Parametros!$B$7,Comissoes_Recebidas!$A:$A,"<="&Parametros!$B$8) -> 0 | H27: =COUNTIFS(Receita_Comissoes!$B:$B,$A27,Receita_Comissoes!$E:$E,"Sim",Receita_Comissoes!$A:$A,">="&Parametros!$B$7,Receita_Comissoes!$A:$A,"<="&Parametros!$B$8) -> 0 | I27: =IF(F27=0,"",(G27*Parametros!$B$6-F27)/F27)
A28: OnSafety | B28: =SUMIFS(Horas!$E:$E,Horas!$C:$C,$A28,Horas!$A:$A,">="&Parametros!$B$7,Horas!$A:$A,"<="&Parametros!$B$8)/60 -> 0 | C28: =SUMIFS(Horas!$G:$G,Horas!$C:$C,$A28,Horas!$A:$A,">="&Parametros!$B$7,Horas!$A:$A,"<="&Parametros!$B$8) -> 0 | D28: =SUMIFS(Receita_Comissoes!$K:$K,Receita_Comissoes!$B:$B,$A28,Receita_Comissoes!$A:$A,">="&Parametros!$B$7,Receita_Comissoes!$A:$A,"<="&Parametros!$B$8)+SUMIFS(Receita_Comissoes!$L:$L,Receita_Comissoes!$B:$B,$A28,Receita_Comissoes!$A:$A,">="&Parametros!$B$7,Receita_Comissoes!$A:$A,"<="&Parametros!$B$8) -> 0 | E28: =SUMIFS(Custos_Diretos!$E:$E,Custos_Diretos!$C:$C,$A28,Custos_Diretos!$A:$A,">="&Parametros!$B$7,Custos_Diretos!$A:$A,"<="&Parametros!$B$8) -> 0 | F28: =C28+D28+E28 -> 0 | G28: =SUMIFS(Receita_Comissoes!$J:$J,Receita_Comissoes!$B:$B,$A28,Receita_Comissoes!$A:$A,">="&Parametros!$B$7,Receita_Comissoes!$A:$A,"<="&Parametros!$B$8)+SUMIFS(Comissoes_Recebidas!$D:$D,Comissoes_Recebidas!$B:$B,$A28,Comissoes_Recebidas!$A:$A,">="&Parametros!$B$7,Comissoes_Recebidas!$A:$A,"<="&Parametros!$B$8) -> 0 | H28: =COUNTIFS(Receita_Comissoes!$B:$B,$A28,Receita_Comissoes!$E:$E,"Sim",Receita_Comissoes!$A:$A,">="&Parametros!$B$7,Receita_Comissoes!$A:$A,"<="&Parametros!$B$8) -> 0 | I28: =IF(F28=0,"",(G28*Parametros!$B$6-F28)/F28)
A29: Have Consultoria | B29: =SUMIFS(Horas!$E:$E,Horas!$C:$C,$A29,Horas!$A:$A,">="&Parametros!$B$7,Horas!$A:$A,"<="&Parametros!$B$8)/60 -> 0 | C29: =SUMIFS(Horas!$G:$G,Horas!$C:$C,$A29,Horas!$A:$A,">="&Parametros!$B$7,Horas!$A:$A,"<="&Parametros!$B$8) -> 0 | D29: =SUMIFS(Receita_Comissoes!$K:$K,Receita_Comissoes!$B:$B,$A29,Receita_Comissoes!$A:$A,">="&Parametros!$B$7,Receita_Comissoes!$A:$A,"<="&Parametros!$B$8)+SUMIFS(Receita_Comissoes!$L:$L,Receita_Comissoes!$B:$B,$A29,Receita_Comissoes!$A:$A,">="&Parametros!$B$7,Receita_Comissoes!$A:$A,"<="&Parametros!$B$8) -> 0 | E29: =SUMIFS(Custos_Diretos!$E:$E,Custos_Diretos!$C:$C,$A29,Custos_Diretos!$A:$A,">="&Parametros!$B$7,Custos_Diretos!$A:$A,"<="&Parametros!$B$8) -> 0 | F29: =C29+D29+E29 -> 0 | G29: =SUMIFS(Receita_Comissoes!$J:$J,Receita_Comissoes!$B:$B,$A29,Receita_Comissoes!$A:$A,">="&Parametros!$B$7,Receita_Comissoes!$A:$A,"<="&Parametros!$B$8)+SUMIFS(Comissoes_Recebidas!$D:$D,Comissoes_Recebidas!$B:$B,$A29,Comissoes_Recebidas!$A:$A,">="&Parametros!$B$7,Comissoes_Recebidas!$A:$A,"<="&Parametros!$B$8) -> 0 | H29: =COUNTIFS(Receita_Comissoes!$B:$B,$A29,Receita_Comissoes!$E:$E,"Sim",Receita_Comissoes!$A:$A,">="&Parametros!$B$7,Receita_Comissoes!$A:$A,"<="&Parametros!$B$8) -> 0 | I29: =IF(F29=0,"",(G29*Parametros!$B$6-F29)/F29)
A30: Prosyst | B30: =SUMIFS(Horas!$E:$E,Horas!$C:$C,$A30,Horas!$A:$A,">="&Parametros!$B$7,Horas!$A:$A,"<="&Parametros!$B$8)/60 -> 0 | C30: =SUMIFS(Horas!$G:$G,Horas!$C:$C,$A30,Horas!$A:$A,">="&Parametros!$B$7,Horas!$A:$A,"<="&Parametros!$B$8) -> 0 | D30: =SUMIFS(Receita_Comissoes!$K:$K,Receita_Comissoes!$B:$B,$A30,Receita_Comissoes!$A:$A,">="&Parametros!$B$7,Receita_Comissoes!$A:$A,"<="&Parametros!$B$8)+SUMIFS(Receita_Comissoes!$L:$L,Receita_Comissoes!$B:$B,$A30,Receita_Comissoes!$A:$A,">="&Parametros!$B$7,Receita_Comissoes!$A:$A,"<="&Parametros!$B$8) -> 0 | E30: =SUMIFS(Custos_Diretos!$E:$E,Custos_Diretos!$C:$C,$A30,Custos_Diretos!$A:$A,">="&Parametros!$B$7,Custos_Diretos!$A:$A,"<="&Parametros!$B$8) -> 0 | F30: =C30+D30+E30 -> 0 | G30: =SUMIFS(Receita_Comissoes!$J:$J,Receita_Comissoes!$B:$B,$A30,Receita_Comissoes!$A:$A,">="&Parametros!$B$7,Receita_Comissoes!$A:$A,"<="&Parametros!$B$8)+SUMIFS(Comissoes_Recebidas!$D:$D,Comissoes_Recebidas!$B:$B,$A30,Comissoes_Recebidas!$A:$A,">="&Parametros!$B$7,Comissoes_Recebidas!$A:$A,"<="&Parametros!$B$8) -> 0 | H30: =COUNTIFS(Receita_Comissoes!$B:$B,$A30,Receita_Comissoes!$E:$E,"Sim",Receita_Comissoes!$A:$A,">="&Parametros!$B$7,Receita_Comissoes!$A:$A,"<="&Parametros!$B$8) -> 0 | I30: =IF(F30=0,"",(G30*Parametros!$B$6-F30)/F30)
A31: P5 Solutions | B31: =SUMIFS(Horas!$E:$E,Horas!$C:$C,$A31,Horas!$A:$A,">="&Parametros!$B$7,Horas!$A:$A,"<="&Parametros!$B$8)/60 -> 0 | C31: =SUMIFS(Horas!$G:$G,Horas!$C:$C,$A31,Horas!$A:$A,">="&Parametros!$B$7,Horas!$A:$A,"<="&Parametros!$B$8) -> 0 | D31: =SUMIFS(Receita_Comissoes!$K:$K,Receita_Comissoes!$B:$B,$A31,Receita_Comissoes!$A:$A,">="&Parametros!$B$7,Receita_Comissoes!$A:$A,"<="&Parametros!$B$8)+SUMIFS(Receita_Comissoes!$L:$L,Receita_Comissoes!$B:$B,$A31,Receita_Comissoes!$A:$A,">="&Parametros!$B$7,Receita_Comissoes!$A:$A,"<="&Parametros!$B$8) -> 0 | E31: =SUMIFS(Custos_Diretos!$E:$E,Custos_Diretos!$C:$C,$A31,Custos_Diretos!$A:$A,">="&Parametros!$B$7,Custos_Diretos!$A:$A,"<="&Parametros!$B$8) -> 0 | F31: =C31+D31+E31 -> 0 | G31: =SUMIFS(Receita_Comissoes!$J:$J,Receita_Comissoes!$B:$B,$A31,Receita_Comissoes!$A:$A,">="&Parametros!$B$7,Receita_Comissoes!$A:$A,"<="&Parametros!$B$8)+SUMIFS(Comissoes_Recebidas!$D:$D,Comissoes_Recebidas!$B:$B,$A31,Comissoes_Recebidas!$A:$A,">="&Parametros!$B$7,Comissoes_Recebidas!$A:$A,"<="&Parametros!$B$8) -> 0 | H31: =COUNTIFS(Receita_Comissoes!$B:$B,$A31,Receita_Comissoes!$E:$E,"Sim",Receita_Comissoes!$A:$A,">="&Parametros!$B$7,Receita_Comissoes!$A:$A,"<="&Parametros!$B$8) -> 0 | I31: =IF(F31=0,"",(G31*Parametros!$B$6-F31)/F31)
A32: Paresi | B32: =SUMIFS(Horas!$E:$E,Horas!$C:$C,$A32,Horas!$A:$A,">="&Parametros!$B$7,Horas!$A:$A,"<="&Parametros!$B$8)/60 -> 0 | C32: =SUMIFS(Horas!$G:$G,Horas!$C:$C,$A32,Horas!$A:$A,">="&Parametros!$B$7,Horas!$A:$A,"<="&Parametros!$B$8) -> 0 | D32: =SUMIFS(Receita_Comissoes!$K:$K,Receita_Comissoes!$B:$B,$A32,Receita_Comissoes!$A:$A,">="&Parametros!$B$7,Receita_Comissoes!$A:$A,"<="&Parametros!$B$8)+SUMIFS(Receita_Comissoes!$L:$L,Receita_Comissoes!$B:$B,$A32,Receita_Comissoes!$A:$A,">="&Parametros!$B$7,Receita_Comissoes!$A:$A,"<="&Parametros!$B$8) -> 0 | E32: =SUMIFS(Custos_Diretos!$E:$E,Custos_Diretos!$C:$C,$A32,Custos_Diretos!$A:$A,">="&Parametros!$B$7,Custos_Diretos!$A:$A,"<="&Parametros!$B$8) -> 0 | F32: =C32+D32+E32 -> 0 | G32: =SUMIFS(Receita_Comissoes!$J:$J,Receita_Comissoes!$B:$B,$A32,Receita_Comissoes!$A:$A,">="&Parametros!$B$7,Receita_Comissoes!$A:$A,"<="&Parametros!$B$8)+SUMIFS(Comissoes_Recebidas!$D:$D,Comissoes_Recebidas!$B:$B,$A32,Comissoes_Recebidas!$A:$A,">="&Parametros!$B$7,Comissoes_Recebidas!$A:$A,"<="&Parametros!$B$8) -> 0 | H32: =COUNTIFS(Receita_Comissoes!$B:$B,$A32,Receita_Comissoes!$E:$E,"Sim",Receita_Comissoes!$A:$A,">="&Parametros!$B$7,Receita_Comissoes!$A:$A,"<="&Parametros!$B$8) -> 0 | I32: =IF(F32=0,"",(G32*Parametros!$B$6-F32)/F32)
A33: Datasoul | B33: =SUMIFS(Horas!$E:$E,Horas!$C:$C,$A33,Horas!$A:$A,">="&Parametros!$B$7,Horas!$A:$A,"<="&Parametros!$B$8)/60 -> 0 | C33: =SUMIFS(Horas!$G:$G,Horas!$C:$C,$A33,Horas!$A:$A,">="&Parametros!$B$7,Horas!$A:$A,"<="&Parametros!$B$8) -> 0 | D33: =SUMIFS(Receita_Comissoes!$K:$K,Receita_Comissoes!$B:$B,$A33,Receita_Comissoes!$A:$A,">="&Parametros!$B$7,Receita_Comissoes!$A:$A,"<="&Parametros!$B$8)+SUMIFS(Receita_Comissoes!$L:$L,Receita_Comissoes!$B:$B,$A33,Receita_Comissoes!$A:$A,">="&Parametros!$B$7,Receita_Comissoes!$A:$A,"<="&Parametros!$B$8) -> 0 | E33: =SUMIFS(Custos_Diretos!$E:$E,Custos_Diretos!$C:$C,$A33,Custos_Diretos!$A:$A,">="&Parametros!$B$7,Custos_Diretos!$A:$A,"<="&Parametros!$B$8) -> 0 | F33: =C33+D33+E33 -> 0 | G33: =SUMIFS(Receita_Comissoes!$J:$J,Receita_Comissoes!$B:$B,$A33,Receita_Comissoes!$A:$A,">="&Parametros!$B$7,Receita_Comissoes!$A:$A,"<="&Parametros!$B$8)+SUMIFS(Comissoes_Recebidas!$D:$D,Comissoes_Recebidas!$B:$B,$A33,Comissoes_Recebidas!$A:$A,">="&Parametros!$B$7,Comissoes_Recebidas!$A:$A,"<="&Parametros!$B$8) -> 0 | H33: =COUNTIFS(Receita_Comissoes!$B:$B,$A33,Receita_Comissoes!$E:$E,"Sim",Receita_Comissoes!$A:$A,">="&Parametros!$B$7,Receita_Comissoes!$A:$A,"<="&Parametros!$B$8) -> 0 | I33: =IF(F33=0,"",(G33*Parametros!$B$6-F33)/F33)
... A42: Habitat Senai/Fiep | B42: =SUMIFS(Horas!$E:$E,Horas!$C:$C,$A42,Horas!$A:$A,">="&Parametros!$B$7,Horas!$A:$A,"<="&Parametros!$B$8)/60 -> 0 | C42: =SUMIFS(Horas!$G:$G,Horas!$C:$C,$A42,Horas!$A:$A,">="&Parametros!$B$7,Horas!$A:$A,"<="&Parametros!$B$8) -> 0 | D42: =SUMIFS(Receita_Comissoes!$K:$K,Receita_Comissoes!$B:$B,$A42,Receita_Comissoes!$A:$A,">="&Parametros!$B$7,Receita_Comissoes!$A:$A,"<="&Parametros!$B$8)+SUMIFS(Receita_Comissoes!$L:$L,Receita_Comissoes!$B:$B,$A42,Receita_Comissoes!$A:$A,">="&Parametros!$B$7,Receita_Comissoes!$A:$A,"<="&Parametros!$B$8) -> 0 | E42: =SUMIFS(Custos_Diretos!$E:$E,Custos_Diretos!$C:$C,$A42,Custos_Diretos!$A:$A,">="&Parametros!$B$7,Custos_Diretos!$A:$A,"<="&Parametros!$B$8) -> 0 | F42: =C42+D42+E42 -> 0 | G42: =SUMIFS(Receita_Comissoes!$J:$J,Receita_Comissoes!$B:$B,$A42,Receita_Comissoes!$A:$A,">="&Parametros!$B$7,Receita_Comissoes!$A:$A,"<="&Parametros!$B$8)+SUMIFS(Comissoes_Recebidas!$D:$D,Comissoes_Recebidas!$B:$B,$A42,Comissoes_Recebidas!$A:$A,">="&Parametros!$B$7,Comissoes_Recebidas!$A:$A,"<="&Parametros!$B$8) -> 0 | H42: =COUNTIFS(Receita_Comissoes!$B:$B,$A42,Receita_Comissoes!$E:$E,"Sim",Receita_Comissoes!$A:$A,">="&Parametros!$B$7,Receita_Comissoes!$A:$A,"<="&Parametros!$B$8) -> 0 | I42: =IF(F42=0,"",(G42*Parametros!$B$6-F42)/F42)
A43: Geral do programa | B43: =SUMIFS(Horas!$E:$E,Horas!$C:$C,$A43,Horas!$A:$A,">="&Parametros!$B$7,Horas!$A:$A,"<="&Parametros!$B$8)/60 -> 4 | C43: =SUMIFS(Horas!$G:$G,Horas!$C:$C,$A43,Horas!$A:$A,">="&Parametros!$B$7,Horas!$A:$A,"<="&Parametros!$B$8) -> 81.818182 | D43: =SUMIFS(Receita_Comissoes!$K:$K,Receita_Comissoes!$B:$B,$A43,Receita_Comissoes!$A:$A,">="&Parametros!$B$7,Receita_Comissoes!$A:$A,"<="&Parametros!$B$8)+SUMIFS(Receita_Comissoes!$L:$L,Receita_Comissoes!$B:$B,$A43,Receita_Comissoes!$A:$A,">="&Parametros!$B$7,Receita_Comissoes!$A:$A,"<="&Parametros!$B$8) -> 0 | E43: =SUMIFS(Custos_Diretos!$E:$E,Custos_Diretos!$C:$C,$A43,Custos_Diretos!$A:$A,">="&Parametros!$B$7,Custos_Diretos!$A:$A,"<="&Parametros!$B$8) -> 0 | F43: =C43+D43+E43 -> 81.818182 | G43: =SUMIFS(Receita_Comissoes!$J:$J,Receita_Comissoes!$B:$B,$A43,Receita_Comissoes!$A:$A,">="&Parametros!$B$7,Receita_Comissoes!$A:$A,"<="&Parametros!$B$8)+SUMIFS(Comissoes_Recebidas!$D:$D,Comissoes_Recebidas!$B:$B,$A43,Comissoes_Recebidas!$A:$A,">="&Parametros!$B$7,Comissoes_Recebidas!$A:$A,"<="&Parametros!$B$8) -> 0 | H43: =COUNTIFS(Receita_Comissoes!$B:$B,$A43,Receita_Comissoes!$E:$E,"Sim",Receita_Comissoes!$A:$A,">="&Parametros!$B$7,Receita_Comissoes!$A:$A,"<="&Parametros!$B$8) -> 0
A44: Total | B44: =SUM(B22:B43) -> 40 | C44: =SUM(C22:C43) -> 818.18182 | D44: =SUM(D22:D43) -> 3000 | E44: =SUM(E22:E43) -> 500 | F44: =SUM(F22:F43) -> 4318.1818 | G44: =SUM(G22:G43) -> 72000 | H44: =SUM(H22:H43) -> 1 | I44: =IF(F44=0,"",(G44*Parametros!$B$6-F44)/F44) -> 15.673684
A45: O total confere com o quadro do período quando todos os lançamentos usam um parceiro desta lista ou Geral do programa.
